<?xml version="1.0" encoding="UTF-8"?>
<monster name="Swordsman Anbu" nameDescription="a swordsman anbu" race="blood" experience="10000" speed="420" manacost="0">
	<health now="15000" max="15000"/>
	<look type="960" corpse="1987"/>
	<targetchange interval="5000" chance="8"/>
	<strategy attack="100" defense="0"/>
	<flags>
		<flag summonable="0"/>
		<flag attackable="1"/>
		<flag hostile="1"/>
		<flag illusionable="0"/>
		<flag convinceable="0"/>
		<flag pushable="0"/>
		<flag canpushitems="1"/>
		<flag canpushcreatures="1"/>
		<flag targetdistance="1"/>
		<flag staticattack="85"/>
		<flag runonhealth="0"/>
	</flags>
	<attacks>
		<attack name="melee" interval="2000" skill="100" attack="240" physical="760"/>
		<attack name="manadrain" interval="2000" chance="25" range="7" min="-925" max="-1800">
			<attribute key="areaEffect" value="blueshimmer"/>
		</attack>
		<attack name="drunk" interval="1000" chance="12" range="1" target="1"/>
		<attack name="lifedrain" interval="2000" chance="10" range="7" min="-880" max="-1760">
		</attack>
	</attacks>
	<defenses armor="32" defense="70">
		<defense name="invisible" interval="2000" chance="10" duration="10000">
			<attribute key="areaEffect" value="redshimmer"/>
		</defense>
		<defense name="healing" interval="2000" chance="20" min="200" max="500">
			<attribute key="areaEffect" value="blueshimmer"/>
		</defense>
		<defense name="speed" interval="1000" chance="35" speedchange="2000" duration="12000">
			<attribute key="areaEffect" value="redshimmer"/>
		</defense>
	</defenses>

	<loot>
		<item id="2148" countmax="90" chance="15000"/><!-- gold coin -->
		<item id="2148" countmax="60" chance="15000"/><!-- gold coin -->
		<item id="2148" countmax="80" chance="15000"/><!-- gold coin -->
		<item id="2152" countmax="5" chanc1="4630"/><!-- platinum coin -->
	

	</loot>
</monster>
